LICENSE.txt
MANIFEST.in
README.md
setup.cfg
setup.py
versioneer.py
microhapdb/__init__.py
microhapdb/_version.py
microhapdb/conftest.py
microhapdb/marker.py
microhapdb/nomenclature.py
microhapdb/panel.py
microhapdb/population.py
microhapdb/tables.py
microhapdb.egg-info/PKG-INFO
microhapdb.egg-info/SOURCES.txt
microhapdb.egg-info/dependency_links.txt
microhapdb.egg-info/entry_points.txt
microhapdb.egg-info/requires.txt
microhapdb.egg-info/top_level.txt
microhapdb.egg-info/zip-safe
microhapdb/cli/__init__.py
microhapdb/cli/frequency.py
microhapdb/cli/lookup.py
microhapdb/cli/marker.py
microhapdb/cli/population.py
microhapdb/cli/summarize.py
microhapdb/data/frequency.csv.gz
microhapdb/data/indels.csv
microhapdb/data/marker-aes.csv
microhapdb/data/marker.csv
microhapdb/data/merged.csv
microhapdb/data/population.csv
microhapdb/tests/test_cli.py
microhapdb/tests/test_frequency.py
microhapdb/tests/test_marker.py
microhapdb/tests/test_nomenclature.py
microhapdb/tests/test_population.py
microhapdb/tests/test_retrieve.py
microhapdb/tests/data/multi2.tsv
microhapdb/tests/data/panel-alpha.fasta
microhapdb/tests/data/panel-beta.fasta