Metadata-Version: 2.1
Name: microhapdb
Version: 0.12
Summary: Portable database of microhaplotype marker and allele frequency data
Home-page: https://github.com/bioforensics/MicroHapDB
Author: Daniel Standage
Author-email: daniel.standage@nbacc.dhs.gov
Classifier: Environment :: Console
Classifier: Framework :: IPython
Classifier: Framework :: Jupyter
Classifier: Intended Audience :: Science/Research
Classifier: Intended Audience :: Legal Industry
Classifier: License :: OSI Approved :: BSD License
Classifier: Programming Language :: Python :: 3
Classifier: Topic :: Scientific/Engineering :: Bio-Informatics
License-File: LICENSE.txt
